README.rst
setup.cfg
setup.py
flask_slackbot/__init__.py
flask_slackbot/base.py
flask_slackbot/exceptions.py
flask_slackbot.egg-info/PKG-INFO
flask_slackbot.egg-info/SOURCES.txt
flask_slackbot.egg-info/dependency_links.txt
flask_slackbot.egg-info/not-zip-safe
flask_slackbot.egg-info/requires.txt
flask_slackbot.egg-info/top_level.txt